Metadata-Version: 2.1
Name: pytest-summary
Version: 0.1.14
Summary: A pytest plugin to send a report and printing summary of tests.
Home-page: https://github.com/Alpaca00/pytest-summary
Author: Oleg Matskiv
Author-email: alpaca00tuha@gmail.com
License: MIT
Keywords: pytest,py.test
Platform: UNKNOWN
Classifier: Framework :: Pytest
Classifier: Development Status :: 5 - Production/Stable
Classifier: Intended Audience :: Developers
Classifier: License :: OSI Approved :: MIT License
Classifier: Natural Language :: English
Classifier: Programming Language :: Python :: 3.7
Classifier: Programming Language :: Python :: 3.8
Classifier: Programming Language :: Python :: 3.9
Classifier: Programming Language :: Python :: 3.10
Requires: pytest
